nbcollection/__init__.py
nbcollection/__main__.py
nbcollection/converter.py
nbcollection/logger.py
nbcollection/nb_helpers.py
nbcollection/notebook.py
nbcollection/commands/__init__.py
nbcollection/commands/argparse_helpers.py
nbcollection/commands/convert.py
nbcollection/commands/execute.py
nbcollection/tests/__init__.py
nbcollection/tests/test_cli.py
nbcollection/tests/data/default.tpl
nbcollection/tests/data/exception-should-fail.ipynb
nbcollection/tests/data/exception-should-pass.ipynb
nbcollection/tests/data/my_notebooks/notebook1.ipynb
nbcollection/tests/data/my_notebooks/sub_path1/notebook2.ipynb
nbcollection/tests/data/my_notebooks/sub_path1/notebook3.ipynb
nbcollection/tests/data/nb_test1/notebook1.ipynb
nbcollection/tests/data/nb_test2/notebook1.ipynb
nbcollection/tests/data/nb_test2/notebook2.ipynb
nbcollection/tests/data/nb_test3/nb1/notebook1.ipynb
nbcollection/tests/data/nb_test3/nb2/notebook2.ipynb
nbcollection-0.2.dist-info/LICENSE
nbcollection-0.2.dist-info/METADATA
nbcollection-0.2.dist-info/WHEEL
nbcollection-0.2.dist-info/entry_points.txt
nbcollection-0.2.dist-info/top_level.txt
nbcollection-0.2.dist-info/RECORD
