Metadata-Version: 2.1
Name: nbcollection
Version: 0.2
Summary: Execute and convert collections of Jupyter notebooks to static HTML
Home-page: https://github.com/adrn/nbcollection
Author: adrn, eteq
Author-email: adrianmpw@gmail.com
License: MIT
Platform: UNKNOWN
Provides: nbcollection
Requires-Python: >=3.6
Requires-Dist: nbconvert
Requires-Dist: jupyter-client
